crimson/code_splitter/__init__.py
crimson/code_splitter/chunker.py
crimson/code_splitter/extractor.py
crimson_code_splitter-0.1.2.dist-info/LICENSE
crimson_code_splitter-0.1.2.dist-info/METADATA
crimson_code_splitter-0.1.2.dist-info/WHEEL
crimson_code_splitter-0.1.2.dist-info/top_level.txt
crimson_code_splitter-0.1.2.dist-info/RECORD
